vsrc/top.v
  module top(
  	input a,
	input b,
	output f
  );
  	assign f = a ^ b;

	initial begin
		$dumpfile("logs/vlt_dump.vcd");
		$dumpvars();
	end
  endmodule

logs/vlt_dump.vcd
$version Generated by VerilatedVcd $end
$date Thu Jul 28 14:08:22 2022 $end
$timescale 1ps $end

 $scope module TOP $end
  $var wire  1 # a $end
  $var wire  1 $ b $end
  $var wire  1 % f $end
  $scope module top $end
   $var wire  1 # a $end
   $var wire  1 $ b $end
   $var wire  1 % f $end
  $upscope $end
 $upscope $end
$enddefinitions $end


#1
1#
0$
1%
#2
1$
0%
#3
#4
0#
0$
#5
1#
1$
#6
0#
1%
#7
#8
1#
0$
#9
0#
0%
#10
#11
1#
1%
#12
1$
0%
#13
0#
0$
#14
1$
1%
#15
1#
0%
#16
0$
1%
#17
0#
0%
#18
1#
1$
#19
0$
1%
#20
#21
1$
0%
#22
#23
0#
1%
#24
0$
0%
#25
1#
1%
#26
#27
#28
0#
1$
#29
0$
0%
#30
1$
1%
#31
1#
0%
#32
0#
1%
#33
#34
#35
1#
0%
#36
0#
1%
#37
#38
#39
0$
0%
#40
1#
1%
#41
#42
0#
0%
#43
#44
1#
1$
#45
0#
1%
#46
0$
0%
#47
#48
1#
1%
#49
0#
0%
#50
1$
1%
#51
1#
0$
#52
0#
0%
#53
1#
1$
#54
0$
1%
#55
#56
0#
0%
#57
1#
1%
#58
0#
1$
#59
1#
0%
#60
0#
1%
#61
#62
1#
0%
#63
#64
#65
#66
0$
1%
#67
1$
0%
#68
0#
1%
#69
#70
1#
0$
#71
0#
1$
#72
#73
1#
0%
#74
0#
0$
#75
1$
1%
#76
#77
#78
#79
#80
1#
0%
#81
0$
1%
#82
0#
0%
#83
1#
1%
#84
#85
0#
0%
#86
#87
1#
1%
#88
1$
0%
#89
#90
0$
1%
#91
0#
1$
#92
1#
0$
#93
1$
0%
#94
0#
1%
#95
#96
1#
0%
#97
#98
0#
0$
#99
1#
1$
#100
0#
1%
#101
0$
0%
#102
1#
1$
#103
0$
1%
#104
0#
0%
#105
#106
#107
1#
1$
#108
0$
1%
#109
0#
1$
#110
#111
#112
#113
0$
0%
#114
1#
1$
#115
0#
0$
#116
1#
1%
#117
0#
0%
#118
1#
1$
#119
0$
1%
#120
0#
1$
#121
0$
0%
#122
1#
1$
#123
0#
0$
#124
#125
1#
1%
#126
1$
0%
#127
0$
1%
#128
0#
1$
#129
0$
0%
#130
#131
1$
1%
#132
0$
0%
#133
#134
1$
1%
#135
0$
0%
#136
#137
1$
1%
#138
1#
0$
#139
0#
1$
#140
1#
0%
#141
0$
1%
#142
#143
0#
1$
#144
1#
0%
#145
0$
1%
#146
1$
0%
#147
0$
1%
#148
0#
1$
#149
0$
0%
#150
#151
#152
#153
1$
1%
#154
1#
0$
#155
#156
#157
0#
0%
#158
1#
1$
#159
0#
0$
#160
1$
1%
#161
#162
1#
0$
#163
1$
0%
#164
#165
0$
1%
#166
1$
0%
#167
0#
1%
#168
1#
0$
#169
#170
0#
0%
#171
#172
1$
1%
#173
#174
0$
0%
#175
#176
#177
1#
1$
#178
0#
1%
#179
0$
0%
#180
1$
1%
#181
0$
0%
#182
#183
1#
1$
#184
0$
1%
#185
0#
1$
#186
0$
0%
#187
1#
1$
#188
0$
1%
#189
0#
1$
#190
0$
0%
#191
1#
1%
#192
1$
0%
#193
#194
0#
1%
#195
1#
0$
#196
0#
1$
#197
0$
0%
#198
#199
1$
1%
#200
0$
0%
#201
1$
1%
#202
0$
0%
#203
#204
#205
1#
1%
#206
1$
0%
#207
0$
1%
#208
0#
0%
#209
1#
1%
#210
0#
1$
#211
0$
0%
#212
1$
1%
#213
1#
0$
#214
1$
0%
#215
#216
0$
1%
#217
0#
1$
#218
0$
0%
#219
1#
1%
#220
1$
0%
#221
0#
0$
#222
1$
1%
#223
0$
0%
#224
1$
1%
#225
0$
0%
#226
#227
1$
1%
#228
1#
0%
#229
0$
1%
#230
0#
1$
#231
#232
1#
0$
#233
1$
0%
#234
0$
1%
#235
#236
1$
0%
#237
0#
1%
#238
1#
0$
#239
1$
0%
#240
#241
0$
1%
#242
0#
1$
#243
1#
0%
#244
0$
1%
#245
0#
1$
#246
1#
0$
#247
#248
0#
0%
#249
1#
1$
#250
0#
0$
#251
1#
1%
#252
0#
1$
#253
1#
0%
#254
#255
0#
1%
#256
#257
1#
0$
#258
0#
0%
#259
1$
1%
#260
0$
0%
#261
1#
1%
#262
0#
0%
#263
#264
#265
#266
1$
1%
#267
0$
0%
#268
1#
1%
#269
#270
1$
0%
#271
#272
0#
0$
#273
1$
1%
#274
0$
0%
#275
1$
1%
#276
#277
1#
0$
#278
1$
0%
#279
0#
1%
#280
1#
0$
#281
0#
0%
#282
#283
1$
1%
#284
0$
0%
#285
1#
1$
#286
#287
0$
1%
#288
1$
0%
#289
0$
1%
#290
1$
0%
#291
#292
0$
1%
#293
#294
1$
0%
#295
0#
1%
#296
0$
0%
#297
1#
1%
#298
0#
1$
#299
1#
0%
#300
0$
1%
#301
0#
1$
#302
1#
0%
#303
#304
0#
0$
#305
1#
1$
#306
0$
1%
#307
0#
0%
#308
1$
1%
#309
1#
0%
#310
#311
0#
1%
#312
1#
0%
#313
#314
0$
1%
#315
0#
0%
#316
1$
1%
#317
1#
0$
#318
0#
0%
#319
1#
1$
#320
0#
0$
#321
#322
1$
1%
#323
0$
0%
#324
1$
1%
#325
1#
0%
#326
0#
0$
#327
1$
1%
#328
1#
0%
#329
0$
1%
#330
1$
0%
#331
0$
1%
#332
0#
0%
#333
1$
1%
#334
1#
0%
#335
0#
1%
#336
1#
0$
#337
1$
0%
#338
0$
1%
#339
#340
#341
#342
0#
0%
#343
1#
1%
#344
#345
0#
1$
#346
#347
1#
0$
#348
0#
1$
#349
1#
0%
#350
0#
1%
#351
#352
0$
0%
#353
1$
1%
#354
#355
1#
0%
#356
#357
0$
1%
#358
1$
0%
#359
0#
0$
#360
1#
1%
#361
1$
0%
#362
0#
0$
#363
#364
1#
1$
#365
#366
#367
0#
1%
#368
1#
0$
#369
0#
1$
#370
1#
0$
#371
1$
0%
#372
0$
1%
#373
#374
1$
0%
#375
0#
1%
#376
1#
0$
#377
0#
1$
#378
0$
0%
#379
1#
1%
#380
0#
0%
#381
1#
1$
#382
0#
0$
#383
1$
1%
#384
0$
0%
#385
1#
1%
#386
0#
0%
#387
1#
1$
#388
0#
0$
#389
1#
1%
#390
#391
#392
0#
1$
#393
0$
0%
#394
1$
1%
#395
0$
0%
#396
#397
1#
1%
#398
0#
1$
#399
1#
0$
#400
#401
0#
0%
#402
1$
1%
#403
1#
0%
#404
#405
0$
1%
#406
#407
1$
0%
#408
#409
#410
0#
0$
#411
1#
1%
#412
0#
0%
#413
#414
1#
1%
#415
0#
1$
#416
#417
1#
0%
#418
0#
0$
#419
#420
1#
1$
#421
0#
0$
#422
1#
1$
#423
0$
1%
#424
0#
1$
#425
#426
1#
0%
#427
#428
0#
0$
#429
1#
1$
#430
0#
1%
#431
0$
0%
#432
1$
1%
#433
1#
0%
#434
0#
1%
#435
1#
0%
#436
0#
1%
#437
#438
1#
0%
#439
0#
1%
#440
0$
0%
#441
1$
1%
#442
1#
0$
#443
0#
1$
#444
#445
1#
0$
#446
1$
0%
#447
0#
1%
#448
1#
0$
#449
0#
1$
#450
1#
0%
#451
0#
0$
#452
1#
1%
#453
#454
0#
1$
#455
1#
0$
#456
#457
0#
1$
#458
0$
0%
#459
#460
1$
1%
#461
#462
1#
0$
#463
0#
0%
#464
1$
1%
#465
1#
0$
#466
0#
1$
#467
#468
#469
1#
0$
#470
1$
0%
#471
0#
0$
#472
1#
1%
#473
1$
0%
#474
0$
1%
#475
1$
0%
#476
#477
0#
0$
#478
1#
1%
#479
0#
0%
#480
1#
1$
#481
0#
0$
#482
1#
1%
#483
1$
0%
#484
#485
0$
1%
#486
0#
1$
#487
1#
0%
#488
0#
0$
#489
1$
1%
#490
#491
0$
0%
#492
#493
1$
1%
#494
#495
1#
0$
#496
0#
1$
#497
#498
1#
0%
#499
0#
1%
#500
#501
1#
0$
#502
#503
1$
0%
#504
#505
0#
1%
#506
0$
0%
#507
1#
1%
#508
0#
0%
#509
#510
1#
1$
#511
0#
1%
#512
1#
0$
#513
#514
0#
1$
#515
1#
0$
#516
1$
0%
#517
0$
1%
#518
#519
#520
0#
1$
#521
0$
0%
#522
1#
1$
#523
#524
#525
0$
1%
#526
0#
0%
#527
1$
1%
#528
#529
0$
0%
#530
1$
1%
#531
1#
0%
#532
0#
0$
#533
1#
1%
#534
0#
0%
#535
#536
1#
1%
#537
#538
0#
0%
#539
1#
1$
#540
#541
0#
1%
#542
1#
0$
#543
1$
0%
#544
#545
0#
1%
#546
#547
1#
0%
#548
0$
1%
#549
1$
0%
#550
#551
0#
0$
#552
1$
1%
#553
1#
0$
#554
#555
#556
1$
0%
#557
0$
1%
#558
#559
0#
0%
#560
1#
1%
#561
0#
0%
#562
1#
1$
#563
0$
1%
#564
#565
#566
1$
0%
#567
#568
0#
0$
#569
1#
1$
#570
0#
1%
#571
1#
0$
#572
0#
1$
#573
0$
0%
#574
1#
1%
#575
0#
1$
#576
0$
0%
#577
1#
1$
#578
0$
1%
#579
1$
0%
#580
0#
1%
#581
1#
0%
#582
0#
0$
#583
1#
1$
#584
0#
0$
#585
1$
1%
#586
1#
0$
#587
#588
1$
0%
#589
0#
0$
#590
#591
1#
1%
#592
#593
0#
0%
#594
1$
1%
#595
1#
0$
#596
0#
1$
#597
#598
1#
0%
#599
0#
0$
#600
1#
1%
#601
1$
0%
#602
0#
0$
#603
1#
1$
#604
#605
0#
1%
#606
1#
0%
#607
0#
0$
#608
#609
1#
1%
#610
#611
#612
1$
0%
#613
#614
0#
1%
#615
1#
0%
#616
0$
1%
#617
0#
0%
#618
1$
1%
#619
1#
0%
#620
0#
1%
#621
1#
0$
#622
1$
0%
#623
0#
1%
#624
1#
0%
#625
0$
1%
#626
0#
0%
#627
1$
1%
#628
1#
0%
#629
0#
1%
#630
#631
1#
0$
#632
1$
0%
#633
0#
1%
#634
1#
0%
#635
#636
0$
1%
#637
#638
#639
#640
#641
0#
1$
#642
1#
0%
#643
0$
1%
#644
0#
1$
#645
#646
1#
0%
#647
0$
1%
#648
0#
1$
#649
#650
#651
1#
0%
#652
0$
1%
#653
#654
0#
0%
#655
#656
1#
1%
#657
#658
#659
0#
0%
#660
#661
1#
1$
#662
0$
1%
#663
#664
1$
0%
#665
#666
0#
0$
#667
1#
1$
#668
0$
1%
#669
1$
0%
#670
#671
0$
1%
#672
0#
1$
#673
#674
1#
0$
#675
1$
0%
#676
0$
1%
#677
0#
0%
#678
#679
1$
1%
#680
1#
0$
#681
#682
0#
0%
#683
1#
1$
#684
0#
1%
#685
1#
0%
#686
0#
0$
#687
1#
1%
#688
1$
0%
#689
0#
1%
#690
#691
#692
#693
1#
0$
#694
#695
0#
0%
#696
1$
1%
#697
0$
0%
#698
1#
1%
#699
0#
1$
#700
1#
0%
#701
#702
0$
1%
#703
0#
1$
#704
0$
0%
#705
#706
1#
1%
#707
1$
0%
#708
0$
1%
#709
0#
0%
#710
#711
1#
1%
#712
1$
0%
#713
0$
1%
#714
1$
0%
#715
0$
1%
#716
0#
0%
#717
1$
1%
#718
1#
0$
#719
0#
1$
#720
0$
0%
#721
1#
1$
#722
0$
1%
#723
#724
0#
1$
#725
1#
0%
#726
0$
1%
#727
#728
#729
0#
1$
#730
1#
0%
#731
#732
0#
1%
#733
1#
0%
#734
#735
0#
1%
#736
#737
1#
0%
#738
0$
1%
#739
1$
0%
#740
0$
1%
#741
0#
0%
#742
#743
#744
#745
1#
1%
#746
#747
1$
0%
#748
0#
0$
#749
1$
1%
#750
0$
0%
#751
1#
1%
#752
#753
#754
0#
0%
#755
1$
1%
#756
1#
0$
#757
1$
0%
#758
0#
1%
#759
1#
0%
#760
0$
1%
#761
#762
#763
0#
1$
#764
1#
0$
#765
0#
1$
#766
1#
0%
#767
0$
1%
#768
#769
1$
0%
#770
0#
1%
#771
#772
1#
0%
#773
0$
1%
#774
0#
0%
#775
1#
1$
#776
0$
1%
#777
0#
0%
#778
#779
1#
1$
#780
0#
1%
#781
#782
1#
0%
#783
0#
0$
#784
1#
1$
#785
0#
0$
#786
#787
1#
1$
#788
0#
0$
#789
1#
1%
#790
#791
0#
0%
#792
#793
1$
1%
#794
#795
0$
0%
#796
1$
1%
#797
#798
0$
0%
#799
#800
1#
1%
#801
0#
1$
#802
#803
0$
0%
#804
#805
1#
1$
#806
0#
1%
#807
1#
0%
#808
#809
0#
1%
#810
0$
0%
#811
1#
1%
#812
1$
0%
#813
0#
0$
#814
1#
1%
#815
0#
0%
#816
#817
1#
1%
#818
#819
1$
0%
#820
0#
0$
#821
#822
1#
1$
#823
0$
1%
#824
0#
1$
#825
1#
0$
#826
0#
0%
#827
1#
1$
#828
0#
1%
#829
1#
0%
#830
#831
0#
1%
#832
1#
0%
#833
#834
0$
1%
#835
0#
1$
#836
#837
#838
#839
1#
0%
#840
0$
1%
#841
1$
0%
#842
0$
1%
#843
0#
1$
#844
1#
0$
#845
0#
0%
#846
1#
1%
#847
1$
0%
#848
0#
1%
#849
#850
1#
0$
#851
#852
1$
0%
#853
0$
1%
#854
0#
1$
#855
1#
0%
#856
0$
1%
#857
0#
0%
#858
1#
1$
#859
0$
1%
#860
#861
#862
0#
0%
#863
1#
1%
#864
1$
0%
#865
0#
1%
#866
#867
1#
0%
#868
0#
0$
#869
1#
1%
#870
#871
0#
1$
#872
1#
0$
#873
#874
1$
0%
#875
0#
0$
#876
1#
1$
#877
#878
0#
0$
#879
1$
1%
#880
0$
0%
#881
#882
1#
1$
#883
#884
0#
1%
#885
1#
0%
#886
#887
0#
0$
#888
#889
1$
1%
#890
1#
0%
#891
0#
0$
#892
1$
1%
#893
1#
0$
#894
1$
0%
#895
0#
1%
#896
1#
0$
#897
#898
0#
1$
#899
1#
0$
#900
0#
1$
#901
1#
0%
#902
0#
0$
#903
#904
#905
1$
1%
#906
1#
0$
#907
#908
#909
0#
0%
#910
#911
1$
1%
#912
1#
0%
#913
0#
1%
#914
#915
1#
0$
#916
0#
0%
#917
1$
1%
#918
0$
0%
#919
1#
1%
#920
0#
1$
#921
1#
0$
#922
#923
0#
0%
#924
1#
1%
#925
1$
0%
#926
#927
0#
0$
#928
#929
1#
1$
#930
0#
0$
#931
1#
1%
#932
0#
1$
#933
1#
0%
#934
#935
0$
1%
#936
0#
1$
#937
0$
0%
#938
1#
1%
#939
0#
0%
#940
1$
1%
#941
1#
0%
#942
0#
0$
#943
1#
1$
#944
0#
0$
#945
#946
1$
1%
#947
1#
0%
#948
0$
1%
#949
0#
0%
#950
1#
1$
#951
0#
0$
#952
#953
#954
#955
1$
1%
#956
0$
0%
#957
#958
#959
1#
1%
#960
0#
1$
#961
1#
0%
#962
0$
1%
#963
0#
0%
#964
#965
#966
1#
1$
#967
0#
0$
#968
1#
1%
#969
0#
0%
#970
#971
1#
1%
#972
0#
1$
#973
1#
0$
#974
#975
#976
0#
0%
#977
1#
1$
#978
0#
1%
#979
1#
0$
#980
1$
0%
#981
0#
0$
#982
#983
#984
#985
1$
1%
#986
1#
0%
#987
#988
0#
0$
#989
#990
1#
1$
#991
0#
1%
#992
1#
0%
#993
0#
1%
#994
#995
1#
0%
#996
0#
0$
#997
1#
1$
#998
0#
0$
#999
1#
1$
#1000
0#
1%
